{".class": "MypyFile", "_fullname": "karabo.util.gpu_util", "is_partial_stub_package": false, "is_stub": false, "names": {".class": "SymbolTable", "__doc__": {".class": "SymbolTableNode", "kind": "Gdef", "node": {".class": "Var", "flags": ["is_ready"], "fullname": "karabo.util.gpu_util.__doc__", "name": "__doc__", "type": "builtins.str"}}, "__file__": {".class": "SymbolTableNode", "kind": "Gdef", "node": {".class": "Var", "flags": ["is_ready"], "fullname": "karabo.util.gpu_util.__file__", "name": "__file__", "type": "builtins.str"}}, "__name__": {".class": "SymbolTableNode", "kind": "Gdef", "node": {".class": "Var", "flags": ["is_ready"], "fullname": "karabo.util.gpu_util.__name__", "name": "__name__", "type": "builtins.str"}}, "__package__": {".class": "SymbolTableNode", "kind": "Gdef", "node": {".class": "Var", "flags": ["is_ready"], "fullname": "karabo.util.gpu_util.__package__", "name": "__package__", "type": "builtins.str"}}, "get_gpu_memory": {".class": "SymbolTableNode", "kind": "Gdef", "node": {".class": "FuncDef", "arg_kinds": [], "arg_names": [], "flags": [], "fullname": "karabo.util.gpu_util.get_gpu_memory", "name": "get_gpu_memory", "type": {".class": "CallableType", "arg_kinds": [], "arg_names": [], "arg_types": [], "bound_args": [], "def_extras": {"first_arg": null}, "fallback": "builtins.function", "implicit": false, "is_ellipsis_args": false, "name": "get_gpu_memory", "ret_type": "builtins.int", "variables": []}}}, "is_cuda_available": {".class": "SymbolTableNode", "kind": "Gdef", "node": {".class": "FuncDef", "arg_kinds": [], "arg_names": [], "flags": [], "fullname": "karabo.util.gpu_util.is_cuda_available", "name": "is_cuda_available", "type": {".class": "CallableType", "arg_kinds": [], "arg_names": [], "arg_types": [], "bound_args": [], "def_extras": {"first_arg": null}, "fallback": "builtins.function", "implicit": false, "is_ellipsis_args": false, "name": "is_cuda_available", "ret_type": "builtins.bool", "variables": []}}}, "os": {".class": "SymbolTableNode", "cross_ref": "os", "kind": "Gdef", "module_hidden": true, "module_public": false}}, "path": "karabo/util/gpu_util.py"}