{".class": "MypyFile", "_fullname": "karabo.error", "is_partial_stub_package": false, "is_stub": false, "names": {".class": "SymbolTable", "KaraboDaskError": {".class": "SymbolTableNode", "kind": "Gdef", "node": {".class": "TypeInfo", "_promote": null, "abstract_attributes": [], "bases": ["karabo.error.KaraboError"], "declared_metaclass": null, "defn": {".class": "ClassDef", "fullname": "karabo.error.KaraboDaskError", "name": "KaraboDaskError", "type_vars": []}, "flags": [], "fullname": "karabo.error.KaraboDaskError", "metaclass_type": null, "metadata": {}, "module_name": "karabo.error", "mro": ["karabo.error.KaraboDaskError", "karabo.error.KaraboError", "builtins.Exception", "builtins.BaseException", "builtins.object"], "names": {".class": "SymbolTable"}, "tuple_type": null, "type_vars": [], "typeddict_type": null}}, "KaraboError": {".class": "SymbolTableNode", "kind": "Gdef", "node": {".class": "TypeInfo", "_promote": null, "abstract_attributes": [], "bases": ["builtins.Exception"], "declared_metaclass": null, "defn": {".class": "ClassDef", "fullname": "karabo.error.KaraboError", "name": "KaraboError", "type_vars": []}, "flags": [], "fullname": "karabo.error.KaraboError", "metaclass_type": null, "metadata": {}, "module_name": "karabo.error", "mro": ["karabo.error.KaraboError", "builtins.Exception", "builtins.BaseException", "builtins.object"], "names": {".class": "SymbolTable"}, "tuple_type": null, "type_vars": [], "typeddict_type": null}}, "KaraboInterferometerSimulationError": {".class": "SymbolTableNode", "kind": "Gdef", "node": {".class": "TypeInfo", "_promote": null, "abstract_attributes": [], "bases": ["karabo.error.KaraboError"], "declared_metaclass": null, "defn": {".class": "ClassDef", "fullname": "karabo.error.KaraboInterferometerSimulationError", "name": "KaraboInterferometerSimulationError", "type_vars": []}, "flags": [], "fullname": "karabo.error.KaraboInterferometerSimulationError", "metaclass_type": null, "metadata": {}, "module_name": "karabo.error", "mro": ["karabo.error.KaraboInterferometerSimulationError", "karabo.error.KaraboError", "builtins.Exception", "builtins.BaseException", "builtins.object"], "names": {".class": "SymbolTable"}, "tuple_type": null, "type_vars": [], "typeddict_type": null}}, "KaraboPinocchioError": {".class": "SymbolTableNode", "kind": "Gdef", "node": {".class": "TypeInfo", "_promote": null, "abstract_attributes": [], "bases": ["karabo.error.KaraboError"], "declared_metaclass": null, "defn": {".class": "ClassDef", "fullname": "karabo.error.KaraboPinocchioError", "name": "KaraboPinocchioError", "type_vars": []}, "flags": [], "fullname": "karabo.error.KaraboPinocchioError", "metaclass_type": null, "metadata": {}, "module_name": "karabo.error", "mro": ["karabo.error.KaraboPinocchioError", "karabo.error.KaraboError", "builtins.Exception", "builtins.BaseException", "builtins.object"], "names": {".class": "SymbolTable"}, "tuple_type": null, "type_vars": [], "typeddict_type": null}}, "KaraboSourceDetectionEvaluationError": {".class": "SymbolTableNode", "kind": "Gdef", "node": {".class": "TypeInfo", "_promote": null, "abstract_attributes": [], "bases": ["karabo.error.KaraboError"], "declared_metaclass": null, "defn": {".class": "ClassDef", "fullname": "karabo.error.KaraboSourceDetectionEvaluationError", "name": "KaraboSourceDetectionEvaluationError", "type_vars": []}, "flags": [], "fullname": "karabo.error.KaraboSourceDetectionEvaluationError", "metaclass_type": null, "metadata": {}, "module_name": "karabo.error", "mro": ["karabo.error.KaraboSourceDetectionEvaluationError", "karabo.error.KaraboError", "builtins.Exception", "builtins.BaseException", "builtins.object"], "names": {".class": "SymbolTable"}, "tuple_type": null, "type_vars": [], "typeddict_type": null}}, "NodeTermination": {".class": "SymbolTableNode", "kind": "Gdef", "node": {".class": "TypeInfo", "_promote": null, "abstract_attributes": [], "bases": ["karabo.error.KaraboError"], "declared_metaclass": null, "defn": {".class": "ClassDef", "fullname": "karabo.error.NodeTermination", "name": "NodeTermination", "type_vars": []}, "flags": [], "fullname": "karabo.error.NodeTermination", "metaclass_type": null, "metadata": {}, "module_name": "karabo.error", "mro": ["karabo.error.NodeTermination", "karabo.error.KaraboError", "builtins.Exception", "builtins.BaseException", "builtins.object"], "names": {".class": "SymbolTable"}, "tuple_type": null, "type_vars": [], "typeddict_type": null}}, "__doc__": {".class": "SymbolTableNode", "kind": "Gdef", "node": {".class": "Var", "flags": ["is_ready"], "fullname": "karabo.error.__doc__", "name": "__doc__", "type": "builtins.str"}}, "__file__": {".class": "SymbolTableNode", "kind": "Gdef", "node": {".class": "Var", "flags": ["is_ready"], "fullname": "karabo.error.__file__", "name": "__file__", "type": "builtins.str"}}, "__name__": {".class": "SymbolTableNode", "kind": "Gdef", "node": {".class": "Var", "flags": ["is_ready"], "fullname": "karabo.error.__name__", "name": "__name__", "type": "builtins.str"}}, "__package__": {".class": "SymbolTableNode", "kind": "Gdef", "node": {".class": "Var", "flags": ["is_ready"], "fullname": "karabo.error.__package__", "name": "__package__", "type": "builtins.str"}}}, "path": "karabo/error.py"}